{"particle_number": 10000, "velocity_min": 0, "velocity_max": 10000, "capture_velocity": 120, "sim_duration_time": 10E-3, "time_step": 2.7E-8, "atom_sort": "Li6", "temperature": 783, "slower_laser_intensity": 0.11, "slower_laser_diameter": 0.01, "slower_laser_frequency": 446799900000000, "slower_laser_saturation": 5.0, "slower_laser_detuning": -130E6, "probe_laser_intensity": 0, "probe_laser_diameter": 0, "probe_laser_frequency": 0, "probe_laser_angle": 5, "laser_polarisation":[0.0, 0.0, 1.0], "positions_for_slicing":[0.0, 0.1, 0.2, 0.3, 0.4, 0.49, 0.495, 0.496, 0.5], "B_field_cutoff": 100.0}